fifo_async.v
module fifo_async #(
  parameter int N_BIT = 8,
  parameter int DEPTH = 16 // DEPTH = 4, 8, 16, ...
)(
  input  logic               wr_clk,
  input  logic               rd_clk,
  input  logic               wr_rst,
  input  logic               rd_rst,

  input  logic [N_BIT-1:0]   wrstream_msg,
  input  logic               wrstream_val,
  output logic               wrstream_rdy,

  output logic [N_BIT-1:0]   rdstream_msg,
  output logic               rdstream_val,
  input  logic               rdstream_rdy,

  output logic               wr_full,
  output logic               rd_empty
);

    localparam int PTRW = $clog2(DEPTH);

    logic [N_BIT-1:0] entries [0:DEPTH-1]; 
    logic [PTRW:0]  rdptr_bin,  wrptr_bin;
    logic [PTRW:0]  rdptr_gray, wrptr_gray;

    logic [PTRW:0] rdptr_gray_ff1, rdptr_gray_ff2;
    logic [PTRW:0] wrptr_gray_ff1, wrptr_gray_ff2;

    logic do_wr, do_rd;
    assign do_wr = wrstream_val && wrstream_rdy;
    assign do_rd = rdstream_val && rdstream_rdy;

    logic [PTRW:0] wrptr_bin_next, rdptr_bin_next;

    always @(*) begin
        if (do_wr) begin
            if (wrptr_bin[PTRW-1:0] == DEPTH-1) begin
                wrptr_bin_next[PTRW-1:0] = 0;
                wrptr_bin_next[PTRW] = ~wrptr_bin[PTRW];
            end else begin
                wrptr_bin_next = wrptr_bin + 1;
            end
        end else begin
            wrptr_bin_next = wrptr_bin;
        end
    end

    always @(*) begin
        if (do_rd) begin
            if (rdptr_bin[PTRW-1:0] == DEPTH-1) begin
                rdptr_bin_next[PTRW-1:0] = 0;
                rdptr_bin_next[PTRW] = ~rdptr_bin[PTRW];
            end else begin
                rdptr_bin_next = rdptr_bin + 1;
            end
        end else begin
            rdptr_bin_next = rdptr_bin;
        end
    end


    always_ff @(posedge wr_clk) begin
        if (wr_rst) begin
            wrptr_bin <= 0;
        end else wrptr_bin <= wrptr_bin_next;
    end

    always_ff @(posedge rd_clk) begin
        if (rd_rst) begin
            rdptr_bin <= 0;
        end else rdptr_bin <= rdptr_bin_next;
    end

    function automatic logic [PTRW:0] bin2gray(input logic [PTRW:0] bin);
        return (bin >> 1) ^ bin;
    endfunction

    assign wrptr_gray = bin2gray(wrptr_bin);
    assign rdptr_gray = bin2gray(rdptr_bin);

    always_ff @(posedge wr_clk) begin
        if (wr_rst) begin
            rdptr_gray_ff1 <= 0;
            rdptr_gray_ff2 <= 0;
        end else begin
            rdptr_gray_ff1 <= rdptr_gray;
            rdptr_gray_ff2 <= rdptr_gray_ff1;
        end
    end

    always_ff @(posedge rd_clk) begin
        if (rd_rst) begin
            wrptr_gray_ff1 <= 0;
            wrptr_gray_ff2 <= 0;
        end else begin
            wrptr_gray_ff1 <= wrptr_gray;
            wrptr_gray_ff2 <= wrptr_gray_ff1;
        end
    end

    function automatic logic is_full(input logic [PTRW:0] wrptr, input logic [PTRW:0] rdptr);
        return (wrptr[PTRW] != rdptr[PTRW]) &&
            (wrptr[PTRW-1] != rdptr[PTRW-1]) &&
            (wrptr[PTRW-2:0] == rdptr[PTRW-2:0]);
    endfunction

    assign rd_empty = (rdptr_gray == wrptr_gray_ff2);
    assign wr_full = is_full(wrptr_gray, rdptr_gray_ff2);

    assign wrstream_rdy = !wr_full;
    assign rdstream_val = !rd_empty;


    always_ff @(posedge wr_clk) begin
        if (do_wr) begin
            entries[wrptr_bin[PTRW-1:0]] <= wrstream_msg;
        end
    end

    assign rdstream_msg = rdstream_val ? entries[rdptr_bin[PTRW-1:0]] : 0;

endmodule

fifo_async_tb.v
`timescale 1ns/1ns

module tb_fifo_async;

  localparam int N_BIT = 8;
  localparam int DEPTH = 16;

  logic               wr_clk;
  logic               rd_clk;
  logic               wr_rst;
  logic               rd_rst;

  logic [N_BIT-1:0]   wrstream_msg;
  logic               wrstream_val;
  logic               wrstream_rdy;

  logic [N_BIT-1:0]   rdstream_msg;
  logic               rdstream_val;
  logic               rdstream_rdy;

  logic               wr_full;
  logic               rd_empty;

  // ------------------------------------------------------------
  // DUT
  // ------------------------------------------------------------
  fifo_async #(
    .N_BIT (N_BIT),
    .DEPTH (DEPTH)
  ) dut (
    .wr_clk       (wr_clk),
    .rd_clk       (rd_clk),
    .wr_rst       (wr_rst),
    .rd_rst       (rd_rst),

    .wrstream_msg (wrstream_msg),
    .wrstream_val (wrstream_val),
    .wrstream_rdy (wrstream_rdy),

    .rdstream_msg (rdstream_msg),
    .rdstream_val (rdstream_val),
    .rdstream_rdy (rdstream_rdy),

    .wr_full      (wr_full),
    .rd_empty     (rd_empty)
  );

  // ------------------------------------------------------------
  // Clock generation
  // wr_clk : 10ns period
  // rd_clk : 30ns period
  // ------------------------------------------------------------
  initial begin
    wr_clk = 1'b0;
    forever #5 wr_clk = ~wr_clk;
  end

  initial begin
    rd_clk = 1'b0;
    forever #15 rd_clk = ~rd_clk;
  end

  // ------------------------------------------------------------
  // Dump waves
  // ------------------------------------------------------------
  initial begin
    $dumpfile("fifo_async_tb.vcd");
    $dumpvars(0, tb_fifo_async);
  end

  // ------------------------------------------------------------
  // Simple reference model / scoreboard
  // ------------------------------------------------------------
  logic [N_BIT-1:0] ref_mem [0:1023];
  logic [N_BIT-1:0] exp_data;

  integer wr_idx;
  integer rd_idx;
  integer num_wr;
  integer num_rd;

  integer released;
  integer remaining;

  // Record every successful write
  always @(posedge wr_clk) begin
    if (!wr_rst && wrstream_val && wrstream_rdy) begin
      ref_mem[wr_idx] = wrstream_msg;
      wr_idx = wr_idx + 1;
      num_wr = num_wr + 1;
      $display("[%0t] WR  data = 0x%02h   total_wr = %0d", $time, wrstream_msg, num_wr);
    end
  end

  // Check every successful read
  always @(posedge rd_clk) begin
    if (!rd_rst && rdstream_val && rdstream_rdy) begin
      if (rd_idx >= wr_idx) begin
        $fatal(1, "[%0t] ERROR: read happened but reference queue is empty", $time);
      end

      exp_data = ref_mem[rd_idx];

      if (rdstream_msg !== exp_data) begin
        $fatal(1,
          "[%0t] ERROR: read mismatch, got = 0x%02h, expected = 0x%02h",
          $time, rdstream_msg, exp_data
        );
      end

      rd_idx = rd_idx + 1;
      num_rd = num_rd + 1;
      $display("[%0t] RD  data = 0x%02h   total_rd = %0d", $time, rdstream_msg, num_rd);
    end
  end

  // ------------------------------------------------------------
  // Tasks
  // ------------------------------------------------------------
  task automatic write_word(input logic [N_BIT-1:0] data);
    begin
      @(negedge wr_clk);
      wrstream_msg = data;
      wrstream_val = 1'b1;

      begin : WAIT_WR_HANDSHAKE
        forever begin
          @(posedge wr_clk);
          if (wrstream_val && wrstream_rdy) begin
            disable WAIT_WR_HANDSHAKE;
          end
        end
      end

      @(negedge wr_clk);
      wrstream_val = 1'b0;
    end
  endtask

  task automatic read_n(input integer n);
    integer cnt;
    begin
      cnt = 0;

      @(negedge rd_clk);
      rdstream_rdy = 1'b1;

      while (cnt < n) begin
        @(posedge rd_clk);
        if (rdstream_val && rdstream_rdy) begin
          cnt = cnt + 1;
        end
      end

      @(negedge rd_clk);
      rdstream_rdy = 1'b0;
    end
  endtask

  // ------------------------------------------------------------
  // Timeout
  // ------------------------------------------------------------
  initial begin
    #5000;
    $fatal(1, "TIMEOUT");
  end

  // ------------------------------------------------------------
  // Main test
  // ------------------------------------------------------------
  initial begin
    wr_rst       = 1'b1;
    rd_rst       = 1'b1;
    wrstream_msg = '0;
    wrstream_val = 1'b0;
    rdstream_rdy = 1'b0;

    wr_idx       = 0;
    rd_idx       = 0;
    num_wr       = 0;
    num_rd       = 0;
    released     = 0;
    remaining    = 0;
    exp_data     = '0;

    // Reset
    repeat (4) @(posedge wr_clk);
    repeat (2) @(posedge rd_clk);

    wr_rst = 1'b0;
    rd_rst = 1'b0;

    // Give CDC synchronizers some time
    repeat (2) @(posedge wr_clk);
    repeat (2) @(posedge rd_clk);

    // --------------------------------------------------------
    // Phase 1: write 6 words, then read 6 words
    // --------------------------------------------------------
    $display("\n================ Phase 1: write 6, read 6 ================\n");

    write_word(8'h00);
    write_word(8'h01);
    write_word(8'h02);
    write_word(8'h03);
    write_word(8'h04);
    write_word(8'h05);

    read_n(6);

    repeat (2) @(posedge rd_clk);
    #1;
    if (rd_empty !== 1'b1) begin
      $fatal(1, "[%0t] ERROR: FIFO should be empty after phase 1", $time);
    end

    // --------------------------------------------------------
    // Phase 2: fill FIFO to full
    // --------------------------------------------------------
    $display("\n================ Phase 2: fill FIFO =======================\n");

    for (integer i = 0; i < DEPTH; i = i + 1) begin
      write_word(8'h80 + i[7:0]);
    end

    @(posedge wr_clk);
    #1;
    if (wr_full !== 1'b1) begin
      $fatal(1, "[%0t] ERROR: FIFO should be full after phase 2", $time);
    end

    // --------------------------------------------------------
    // Phase 3: try one extra write while full
    // it should be blocked first, then accepted after some reads
    // --------------------------------------------------------
    $display("\n================ Phase 3: extra write under full ==========\n");

    @(negedge wr_clk);
    wrstream_msg = 8'hF0;
    wrstream_val = 1'b1;

    // While FIFO is still full, wrstream_rdy should stay low
    repeat (3) begin
      @(posedge wr_clk);
      #1;
      if (wrstream_rdy !== 1'b0) begin
        $fatal(1, "[%0t] ERROR: wrstream_rdy should be 0 while FIFO is full", $time);
      end
    end

    released = 0;

    fork
      begin
        // start reading 4 entries to make room
        read_n(4);
      end

      begin : WAIT_EXTRA_ACCEPT
        repeat (20) begin
          @(posedge wr_clk);
          if (wrstream_val && wrstream_rdy) begin
            released = 1;
            $display("[%0t] Extra write accepted after full condition cleared", $time);
            disable WAIT_EXTRA_ACCEPT;
          end
        end
      end
    join

    if (released == 0) begin
      $fatal(1, "[%0t] ERROR: extra write was not accepted in time", $time);
    end

    @(negedge wr_clk);
    wrstream_val = 1'b0;

    // --------------------------------------------------------
    // Phase 4: drain everything
    // --------------------------------------------------------
    remaining = wr_idx - rd_idx;
    $display("\n================ Phase 4: drain remaining %0d words =======\n", remaining);

    read_n(remaining);

    repeat (2) @(posedge rd_clk);
    #1;
    if (rd_empty !== 1'b1) begin
      $fatal(1, "[%0t] ERROR: FIFO should be empty at end of test", $time);
    end

    if (wr_idx !== rd_idx) begin
      $fatal(1, "[%0t] ERROR: write count != read count (%0d vs %0d)",
             $time, wr_idx, rd_idx);
    end

    $display("\n===========================================================");
    $display("PASS: all checks passed");
    $display("total writes = %0d, total reads = %0d", num_wr, num_rd);
    $display("===========================================================\n");

    #20;
    $finish;
  end

  initial begin
    $dumpfile("fifo_async_tb.vcd");
    $dumpvars(0, tb_fifo_async);
  end

endmodule

build/fifo_async_tb.vcd
$date
	Tue Mar 17 22:33:09 2026
$end
$version
	Icarus Verilog
$end
$timescale
	1ns
$end
$scope module tb_fifo_async $end
$var wire 1 ! wrstream_rdy $end
$var wire 1 " wr_full $end
$var wire 1 # rdstream_val $end
$var wire 8 $ rdstream_msg [7:0] $end
$var wire 1 % rd_empty $end
$var parameter 32 & DEPTH $end
$var parameter 32 ' N_BIT $end
$var reg 8 ( exp_data [7:0] $end
$var reg 1 ) rd_clk $end
$var reg 1 * rd_rst $end
$var reg 1 + rdstream_rdy $end
$var reg 1 , wr_clk $end
$var reg 1 - wr_rst $end
$var reg 8 . wrstream_msg [7:0] $end
$var reg 1 / wrstream_val $end
$var integer 32 0 num_rd [31:0] $end
$var integer 32 1 num_wr [31:0] $end
$var integer 32 2 rd_idx [31:0] $end
$var integer 32 3 released [31:0] $end
$var integer 32 4 remaining [31:0] $end
$var integer 32 5 wr_idx [31:0] $end
$scope module dut $end
$var wire 1 6 do_rd $end
$var wire 1 7 do_wr $end
$var wire 1 ) rd_clk $end
$var wire 1 * rd_rst $end
$var wire 1 + rdstream_rdy $end
$var wire 1 , wr_clk $end
$var wire 1 - wr_rst $end
$var wire 8 8 wrstream_msg [7:0] $end
$var wire 1 / wrstream_val $end
$var wire 1 ! wrstream_rdy $end
$var wire 5 9 wrptr_gray [4:0] $end
$var wire 1 " wr_full $end
$var wire 1 # rdstream_val $end
$var wire 8 : rdstream_msg [7:0] $end
$var wire 5 ; rdptr_gray [4:0] $end
$var wire 1 % rd_empty $end
$var parameter 32 < DEPTH $end
$var parameter 32 = N_BIT $end
$var parameter 32 > PTRW $end
$var reg 5 ? rdptr_bin [4:0] $end
$var reg 5 @ rdptr_bin_next [4:0] $end
$var reg 5 A rdptr_gray_ff1 [4:0] $end
$var reg 5 B rdptr_gray_ff2 [4:0] $end
$var reg 5 C wrptr_bin [4:0] $end
$var reg 5 D wrptr_bin_next [4:0] $end
$var reg 5 E wrptr_gray_ff1 [4:0] $end
$var reg 5 F wrptr_gray_ff2 [4:0] $end
$scope function bin2gray $end
$upscope $end
$scope function is_full $end
$upscope $end
$upscope $end
$scope begin $ivl_for_loop0 $end
$var integer 32 G i [31:0] $end
$upscope $end
$scope begin WAIT_EXTRA_ACCEPT $end
$upscope $end
$scope task read_n $end
$upscope $end
$scope task write_word $end
$scope begin WAIT_WR_HANDSHAKE $end
$upscope $end
$upscope $end
$upscope $end
$scope module tb_fifo_async $end
$scope module dut $end
$scope function bin2gray $end
$upscope $end
$scope function is_full $end
$upscope $end
$upscope $end
$scope begin $ivl_for_loop0 $end
$upscope $end
$scope begin WAIT_EXTRA_ACCEPT $end
$upscope $end
$scope task read_n $end
$upscope $end
$scope task write_word $end
$scope begin WAIT_WR_HANDSHAKE $end
$upscope $end
$upscope $end
$upscope $end
$enddefinitions $end
$comment Show the parameter values. $end
$dumpall
b100 >
b1000 =
b10000 <
b1000 '
b10000 &
$end
#0
$dumpvars
bx G
bx F
bx E
bx D
bx C
bx B
bx A
bx @
bx ?
bx ;
bx :
bx 9
b0 8
07
06
b0 5
b0 4
b0 3
b0 2
b0 1
b0 0
0/
b0 .
1-
0,
0+
1*
0)
b0 (
x%
bx $
x#
x"
x!
$end
#5
1!
0"
b0 D
b0 9
b0 C
b0 B
b0 A
1,
#10
0,
#15
b0 $
b0 :
b0 @
0#
1%
b0 ;
b0 ?
b0 F
b0 E
1,
1)
#20
0,
#25
1,
#30
0,
0)
#35
1,
#40
0,
#45
1,
1)
#50
0,
#55
1,
#60
0,
0)
#65
1,
#70
0,
#75
0*
0-
1,
1)
#80
0,
#85
1,
#90
0,
0)
#95
1,
#100
0,
#105
1,
1)
#110
0,
#115
1,
#120
0,
0)
#125
1,
#130
0,
#135
1,
1)
#140
b1 D
17
1/
0,
#145
b10 D
b1 9
b1 C
b1 1
b1 5
1,
#150
b1 D
07
0/
0,
0)
#155
1,
#160
b10 D
17
1/
b1 .
b1 8
0,
#165
b11 D
b11 9
b10 C
b1 E
b10 1
b10 5
1,
1)
#170
b10 D
07
0/
0,
#175
1,
#180
b11 D
17
1/
b10 .
b10 8
0,
0)
#185
b100 D
b10 9
b11 C
b11 1
b11 5
1,
#190
b11 D
07
0/
0,
#195
1#
0%
b1 F
b10 E
1,
1)
#200
b100 D
17
1/
b11 .
b11 8
0,
#205
b101 D
b110 9
b100 C
b100 1
b100 5
1,
#210
b100 D
07
0/
0,
0)
#215
1,
#220
b101 D
17
1/
b100 .
b100 8
0,
#225
b110 D
b111 9
b101 C
b10 F
b110 E
b101 1
b101 5
1,
1)
#230
b101 D
07
0/
0,
#235
1,
#240
b110 D
17
1/
b101 .
b101 8
0,
0)
#245
b111 D
b101 9
b110 C
b110 1
b110 5
1,
#250
b110 D
07
0/
0,
#255
b110 F
b101 E
1,
1)
#260
0,
#265
1,
#270
b1 @
16
1+
0,
0)
#275
1,
#280
0,
#285
b1 $
b1 :
b10 @
b1 ;
b101 F
b1 ?
b1 0
b1 2
1,
1)
#290
0,
#295
b1 A
1,
#300
0,
0)
#305
b1 B
1,
#310
0,
#315
b10 $
b10 :
b11 @
b11 ;
b10 ?
b10 0
b10 2
b1 (
1,
1)
#320
0,
#325
b11 A
1,
#330
0,
0)
#335
b11 B
1,
#340
0,
#345
b11 $
b11 :
b100 @
b10 ;
b11 ?
b11 0
b11 2
b10 (
1,
1)
#350
0,
#355
b10 A
1,
#360
0,
0)
#365
b10 B
1,
#370
0,
#375
b100 $
b100 :
b101 @
b110 ;
b100 ?
b100 0
b100 2
b11 (
1,
1)
#380
0,
#385
b110 A
1,
#390
0,
0)
#395
b110 B
1,
#400
0,
#405
b101 $
b101 :
b110 @
b111 ;
b101 ?
b101 0
b101 2
b100 (
1,
1)
#410
0,
#415
b111 A
1,
#420
0,
0)
#425
b111 B
1,
#430
0,
#435
06
b0 $
b0 :
b110 @
0#
1%
b101 ;
b110 ?
b110 0
b110 2
b101 (
1,
1)
#440
0,
#445
b101 A
1,
#450
0+
0,
0)
#455
b101 B
1,
#460
0,
#465
1,
1)
#470
0,
#475
1,
#480
0,
0)
#485
1,
#490
0,
#495
1,
1)
#496
b0 G
#500
b111 D
17
1/
b10000000 .
b10000000 8
0,
#505
b1000 D
b100 9
b111 C
b111 1
b111 5
1,
#510
b111 D
07
b1 G
0/
0,
0)
#515
1,
#520
b1000 D
17
1/
b10000001 .
b10000001 8
0,
#525
b1001 D
b1100 9
b1000 C
b100 E
b1000 1
b1000 5
1,
1)
#530
b1000 D
07
b10 G
0/
0,
#535
1,
#540
b1001 D
17
1/
b10000010 .
b10000010 8
0,
0)
#545
b1010 D
b1101 9
b1001 C
b1001 1
b1001 5
1,
#550
b1001 D
07
b11 G
0/
0,
#555
b10000000 $
b10000000 :
1#
0%
b100 F
b1101 E
1,
1)
#560
b1010 D
17
1/
b10000011 .
b10000011 8
0,
#565
b1011 D
b1111 9
b1010 C
b1010 1
b1010 5
1,
#570
b1010 D
07
b100 G
0/
0,
0)
#575
1,
#580
b1011 D
17
1/
b10000100 .
b10000100 8
0,
#585
b1100 D
b1110 9
b1011 C
b1101 F
b1111 E
b1011 1
b1011 5
1,
1)
#590
b1011 D
07
b101 G
0/
0,
#595
1,
#600
b1100 D
17
1/
b10000101 .
b10000101 8
0,
0)
#605
b1101 D
b1010 9
b1100 C
b1100 1
b1100 5
1,
#610
b1100 D
07
b110 G
0/
0,
#615
b1111 F
b1010 E
1,
1)
#620
b1101 D
17
1/
b10000110 .
b10000110 8
0,
#625
b1110 D
b1011 9
b1101 C
b1101 1
b1101 5
1,
#630
b1101 D
07
b111 G
0/
0,
0)
#635
1,
#640
b1110 D
17
1/
b10000111 .
b10000111 8
0,
#645
b1111 D
b1001 9
b1110 C
b1010 F
b1011 E
b1110 1
b1110 5
1,
1)
#650
b1110 D
07
b1000 G
0/
0,
#655
1,
#660
b1111 D
17
1/
b10001000 .
b10001000 8
0,
0)
#665
b10000 D
b1000 9
b1111 C
b1111 1
b1111 5
1,
#670
b1111 D
07
b1001 G
0/
0,
#675
b1011 F
b1000 E
1,
1)
#680
b10000 D
17
1/
b10001001 .
b10001001 8
0,
#685
b10001 D
b11000 9
b10000 C
b10000 1
b10000 5
1,
#690
b10000 D
07
b1010 G
0/
0,
0)
#695
1,
#700
b10001 D
17
1/
b10001010 .
b10001010 8
0,
#705
b10010 D
b11001 9
b10001 C
b1000 F
b11000 E
b10001 1
b10001 5
1,
1)
#710
b10001 D
07
b1011 G
0/
0,
#715
1,
#720
b10010 D
17
1/
b10001011 .
b10001011 8
0,
0)
#725
b10011 D
b11011 9
b10010 C
b10010 1
b10010 5
1,
#730
b10010 D
07
b1100 G
0/
0,
#735
b11000 F
b11011 E
1,
1)
#740
b10011 D
17
1/
b10001100 .
b10001100 8
0,
#745
b10100 D
b11010 9
b10011 C
b10011 1
b10011 5
1,
#750
b10011 D
07
b1101 G
0/
0,
0)
#755
1,
#760
b10100 D
17
1/
b10001101 .
b10001101 8
0,
#765
b10101 D
b11110 9
b10100 C
b11011 F
b11010 E
b10100 1
b10100 5
1,
1)
#770
b10100 D
07
b1110 G
0/
0,
#775
1,
#780
b10101 D
17
1/
b10001110 .
b10001110 8
0,
0)
#785
b10110 D
b11111 9
b10101 C
b10101 1
b10101 5
1,
#790
b10101 D
07
b1111 G
0/
0,
#795
b11010 F
b11111 E
1,
1)
#800
b10110 D
17
1/
b10001111 .
b10001111 8
0,
#805
07
0!
1"
b10110 D
b11101 9
b10110 C
b10110 1
b10110 5
1,
#810
b10000 G
0/
0,
0)
#815
1,
#820
1/
b11110000 .
b11110000 8
0,
#825
b11111 F
b11101 E
1,
1)
#830
0,
#835
1,
#840
0,
0)
#845
1,
#850
0,
#855
b11101 F
1,
1)
#860
0,
#865
1,
#870
b111 @
16
1+
0,
0)
#875
1,
#880
0,
#885
b10000001 $
b10000001 :
b1000 @
b100 ;
b111 ?
b111 0
b111 2
b10000000 (
1,
1)
#890
0,
#895
b100 A
1,
#900
0,
0)
#905
b10111 D
17
1!
0"
b100 B
1,
#910
0,
#915
07
0!
1"
b10000010 $
b10000010 :
b10111 D
b11100 9
b1001 @
b1100 ;
b10111 C
b1000 ?
b10111 1
b10111 5
b1 3
b1000 0
b1000 2
b10000001 (
1,
1)
#920
0,
#925
b1100 A
1,
#930
0,
0)
#935
b11000 D
17
1!
0"
b1100 B
1,
#940
0,
#945
07
0!
1"
b10000011 $
b10000011 :
b11000 D
b10100 9
b1010 @
b1101 ;
b11000 C
b11100 E
b1001 ?
b11000 1
b11000 5
b1001 0
b1001 2
b10000010 (
1,
1)
#950
0,
#955
b1101 A
1,
#960
0,
0)
#965
b11001 D
17
1!
0"
b1101 B
1,
#970
0,
#975
07
0!
1"
b10000100 $
b10000100 :
b11001 D
b10101 9
b1011 @
b1111 ;
b11001 C
b1010 ?
b11100 F
b10100 E
b11001 1
b11001 5
b1010 0
b1010 2
b10000011 (
1,
1)
#980
0,
#985
b1111 A
1,
#990
b1010 @
06
0+
0,
0)
#995
b11010 D
17
1!
0"
b1111 B
1,
#1000
b11001 D
07
b1111 4
0/
0,
#1005
b10100 F
b10101 E
1,
1)
#1010
0,
#1015
1,
#1020
b1011 @
16
1+
0,
0)
#1025
1,
#1030
0,
#1035
b10000101 $
b10000101 :
b1100 @
b1110 ;
b1011 ?
b10101 F
b1011 0
b1011 2
b10000100 (
1,
1)
#1040
0,
#1045
b1110 A
1,
#1050
0,
0)
#1055
b1110 B
1,
#1060
0,
#1065
b10000110 $
b10000110 :
b1101 @
b1010 ;
b1100 ?
b1100 0
b1100 2
b10000101 (
1,
1)
#1070
0,
#1075
b1010 A
1,
#1080
0,
0)
#1085
b1010 B
1,
#1090
0,
#1095
b10000111 $
b10000111 :
b1110 @
b1011 ;
b1101 ?
b1101 0
b1101 2
b10000110 (
1,
1)
#1100
0,
#1105
b1011 A
1,
#1110
0,
0)
#1115
b1011 B
1,
#1120
0,
#1125
b10001000 $
b10001000 :
b1111 @
b1001 ;
b1110 ?
b1110 0
b1110 2
b10000111 (
1,
1)
#1130
0,
#1135
b1001 A
1,
#1140
0,
0)
#1145
b1001 B
1,
#1150
0,
#1155
b10001001 $
b10001001 :
b10000 @
b1000 ;
b1111 ?
b1111 0
b1111 2
b10001000 (
1,
1)
#1160
0,
#1165
b1000 A
1,
#1170
0,
0)
#1175
b1000 B
1,
#1180
0,
#1185
b10001010 $
b10001010 :
b10001 @
b11000 ;
b10000 ?
b10000 0
b10000 2
b10001001 (
1,
1)
#1190
0,
#1195
b11000 A
1,
#1200
0,
0)
#1205
b11000 B
1,
#1210
0,
#1215
b10001011 $
b10001011 :
b10010 @
b11001 ;
b10001 ?
b10001 0
b10001 2
b10001010 (
1,
1)
#1220
0,
#1225
b11001 A
1,
#1230
0,
0)
#1235
b11001 B
1,
#1240
0,
#1245
b10001100 $
b10001100 :
b10011 @
b11011 ;
b10010 ?
b10010 0
b10010 2
b10001011 (
1,
1)
#1250
0,
#1255
b11011 A
1,
#1260
0,
0)
#1265
b11011 B
1,
#1270
0,
#1275
b10001101 $
b10001101 :
b10100 @
b11010 ;
b10011 ?
b10011 0
b10011 2
b10001100 (
1,
1)
#1280
0,
#1285
b11010 A
1,
#1290
0,
0)
#1295
b11010 B
1,
#1300
0,
#1305
b10001110 $
b10001110 :
b10101 @
b11110 ;
b10100 ?
b10100 0
b10100 2
b10001101 (
1,
1)
#1310
0,
#1315
b11110 A
1,
#1320
0,
0)
#1325
b11110 B
1,
#1330
0,
#1335
b10001111 $
b10001111 :
b10110 @
b11111 ;
b10101 ?
b10101 0
b10101 2
b10001110 (
1,
1)
#1340
0,
#1345
b11111 A
1,
#1350
0,
0)
#1355
b11111 B
1,
#1360
0,
#1365
b11110000 $
b11110000 :
b10111 @
b11101 ;
b10110 ?
b10110 0
b10110 2
b10001111 (
1,
1)
#1370
0,
#1375
b11101 A
1,
#1380
0,
0)
#1385
b11101 B
1,
#1390
0,
#1395
b11000 @
b11100 ;
b10111 ?
b10111 0
b10111 2
b11110000 (
1,
1)
#1400
0,
#1405
b11100 A
1,
#1410
0,
0)
#1415
b11100 B
1,
#1420
0,
#1425
b11001 @
b10100 ;
b11000 ?
b11000 0
b11000 2
1,
1)
#1430
0,
#1435
b10100 A
1,
#1440
0,
0)
#1445
b10100 B
1,
#1450
0,
#1455
06
b0 $
b0 :
b11001 @
0#
1%
b10101 ;
b11001 ?
b11001 0
b11001 2
1,
1)
#1460
0,
#1465
b10101 A
1,
#1470
0+
0,
0)
#1475
b10101 B
1,
